legendmeta/__init__.py
legendmeta/_version.py
legendmeta/catalog.py
legendmeta/core.py
legendmeta/police.py
legendmeta/scdb_tables.py
legendmeta/slowcontrol.py
legendmeta/templates/bege-detector.yaml
legendmeta/templates/coax-detector.yaml
legendmeta/templates/geds-channel.yaml
legendmeta/templates/icpc-detector.yaml
legendmeta/templates/ppc-detector.yaml
legendmeta/templates/spms-channel.yaml
pylegendmeta-1.3.4.dist-info/licenses/LICENSE
pylegendmeta-1.3.4.dist-info/METADATA
pylegendmeta-1.3.4.dist-info/WHEEL
pylegendmeta-1.3.4.dist-info/entry_points.txt
pylegendmeta-1.3.4.dist-info/top_level.txt
pylegendmeta-1.3.4.dist-info/RECORD
