Metadata-Version: 2.4
Name: pylegendmeta
Version: 1.3.4
Summary: Python LEGEND-metadata implementation
Author-email: Luigi Pertoldi <gipert@pm.me>
Maintainer: The LEGEND Collaboration
License: GPL-3.0
Project-URL: Homepage, https://github.com/legend-exp/pylegendmeta
Project-URL: Bug Tracker, https://github.com/legend-exp/pylegedmeta/issues
Project-URL: Discussions, https://github.com/legend-exp/pylegedmeta/discussions
Project-URL: Changelog, https://github.com/legend-exp/pylegedmeta/releases
Classifier: Development Status :: 4 - Beta
Classifier: Intended Audience :: Developers
Classifier: Intended Audience :: Science/Research
Classifier: License :: OSI Approved :: GNU General Public License v3 (GPLv3)
Classifier: Operating System :: MacOS
Classifier: Operating System :: POSIX
Classifier: Operating System :: Unix
Classifier: Programming Language :: Python
Classifier: Programming Language :: Python :: 3
Classifier: Programming Language :: Python :: 3 :: Only
Classifier: Topic :: Scientific/Engineering
Requires-Python: >=3.9
License-File: LICENSE
Requires-Dist: packaging
Requires-Dist: dbetto>=1.2.2
Requires-Dist: GitPython
Requires-Dist: pandas
Requires-Dist: pyyaml
Requires-Dist: psycopg2-binary<=2.9.9; python_version < "3.10" and platform_system == "Darwin"
Requires-Dist: psycopg2-binary; python_version >= "3.10" or platform_system != "Darwin"
Requires-Dist: sqlalchemy>=2
Provides-Extra: all
Requires-Dist: pylegendmeta[docs,test]; extra == "all"
Provides-Extra: docs
Requires-Dist: furo; extra == "docs"
Requires-Dist: myst-parser; extra == "docs"
Requires-Dist: sphinx>=7.2.2; extra == "docs"
Requires-Dist: sphinx-copybutton; extra == "docs"
Requires-Dist: sphinx-inline-tabs; extra == "docs"
Provides-Extra: test
Requires-Dist: pre-commit; extra == "test"
Requires-Dist: pytest>=6.0; extra == "test"
Requires-Dist: pytest-cov; extra == "test"
Dynamic: license-file
